splych/__init__.py
splych-0.0.5.dist-info/LICENSE
splych-0.0.5.dist-info/METADATA
splych-0.0.5.dist-info/WHEEL
splych-0.0.5.dist-info/top_level.txt
splych-0.0.5.dist-info/RECORD
